{
  "_meta": {
    "filetypes": [],
    "has_aggregate": false,
    "has_provision": true,
    "has_write": false,
    "resources": [
      "box",
      "chroma",
      "databricks_volume",
      "dify",
      "discord",
      "dropbox",
      "gdocs",
      "gdrive",
      "github",
      "github_ci",
      "gmail",
      "gsheets",
      "gslides",
      "lancedb",
      "langfuse",
      "linear",
      "mongodb",
      "notion",
      "opfs",
      "postgres",
      "qdrant",
      "ram",
      "s3",
      "slack",
      "trello"
    ]
  },
  "description": null,
  "ignore_tokens": [],
  "options": [
    {
      "description": null,
      "long": "--width",
      "numeric_shorthand": false,
      "repeatable": false,
      "short": "-w",
      "value_kind": "text",
      "value_optional": false
    },
    {
      "description": null,
      "long": "--goal",
      "numeric_shorthand": false,
      "repeatable": false,
      "short": "-g",
      "value_kind": "text",
      "value_optional": false
    },
    {
      "description": null,
      "long": "--crown-margin",
      "numeric_shorthand": false,
      "repeatable": false,
      "short": "-c",
      "value_kind": "none",
      "value_optional": false
    },
    {
      "description": null,
      "long": "--prefix",
      "numeric_shorthand": false,
      "repeatable": false,
      "short": "-p",
      "value_kind": "text",
      "value_optional": false
    },
    {
      "description": null,
      "long": "--split-only",
      "numeric_shorthand": false,
      "repeatable": false,
      "short": "-s",
      "value_kind": "none",
      "value_optional": false
    },
    {
      "description": null,
      "long": "--tagged-paragraph",
      "numeric_shorthand": false,
      "repeatable": false,
      "short": "-t",
      "value_kind": "none",
      "value_optional": false
    },
    {
      "description": null,
      "long": "--uniform-spacing",
      "numeric_shorthand": false,
      "repeatable": false,
      "short": "-u",
      "value_kind": "none",
      "value_optional": false
    }
  ],
  "positional": [],
  "rest": {
    "kind": "path",
    "provided_by": []
  }
}
