{
  "cases": [
    {
      "id": "subshell_positional_isolated",
      "seq": 512,
      "targets": [
        "ram",
        "disk",
        "redis",
        "opfs",
        "s3",
        "databricks",
        "gridfs",
        "s3-prefix",
        "databricks-prefix",
        "gridfs-prefix",
        "hf",
        "hf-prefix",
        "dropbox",
        "dropbox-root",
        "onedrive",
        "sharepoint",
        "sharepoint-prefix",
        "ssh",
        "nextcloud",
        "gdrive",
        "gdrive-folder",
        "box"
      ],
      "command": "(set -- a b c; (set -- x); echo $#)",
      "expect": {
        "exit": 0,
        "stdout": "3\n",
        "stderr": ""
      }
    },
    {
      "id": "subshell_positional_inherit",
      "seq": 513,
      "targets": [
        "ram",
        "disk",
        "redis",
        "opfs",
        "s3",
        "databricks",
        "gridfs",
        "s3-prefix",
        "databricks-prefix",
        "gridfs-prefix",
        "hf",
        "hf-prefix",
        "dropbox",
        "dropbox-root",
        "onedrive",
        "sharepoint",
        "sharepoint-prefix",
        "ssh",
        "nextcloud",
        "gdrive",
        "gdrive-folder",
        "box"
      ],
      "command": "(set -- a b; (echo $1 $2))",
      "expect": {
        "exit": 0,
        "stdout": "a b\n",
        "stderr": ""
      }
    }
  ]
}
