{
  "cases": [
    {
      "id": "herestring_basic",
      "seq": 501219,
      "targets": [
        "ram",
        "disk",
        "redis",
        "opfs",
        "s3",
        "databricks",
        "s3-prefix",
        "databricks-prefix",
        "hf",
        "hf-prefix",
        "dropbox",
        "dropbox-root",
        "onedrive",
        "sharepoint",
        "sharepoint-prefix",
        "ssh",
        "nextcloud",
        "gdrive",
        "gdrive-folder"
      ],
      "command": "cat <<< hi",
      "expect": {
        "exit": 0,
        "stdout": "hi\n",
        "stderr": ""
      }
    },
    {
      "id": "herestring_quoted",
      "seq": 501220,
      "targets": [
        "ram",
        "disk",
        "redis",
        "opfs",
        "s3",
        "databricks",
        "s3-prefix",
        "databricks-prefix",
        "hf",
        "hf-prefix",
        "dropbox",
        "dropbox-root",
        "onedrive",
        "sharepoint",
        "sharepoint-prefix",
        "ssh",
        "nextcloud",
        "gdrive",
        "gdrive-folder"
      ],
      "command": "cat <<< \"two words\"",
      "expect": {
        "exit": 0,
        "stdout": "two words\n",
        "stderr": ""
      }
    },
    {
      "id": "herestring_single_quoted",
      "seq": 501221,
      "targets": [
        "ram",
        "disk",
        "redis",
        "opfs",
        "s3",
        "databricks",
        "s3-prefix",
        "databricks-prefix",
        "hf",
        "hf-prefix",
        "dropbox",
        "dropbox-root",
        "onedrive",
        "sharepoint",
        "sharepoint-prefix",
        "ssh",
        "nextcloud",
        "gdrive",
        "gdrive-folder"
      ],
      "command": "cat <<< 'single $notexp'",
      "expect": {
        "exit": 0,
        "stdout": "single $notexp\n",
        "stderr": ""
      }
    },
    {
      "id": "herestring_var",
      "seq": 501222,
      "targets": [
        "ram",
        "disk",
        "redis",
        "opfs",
        "s3",
        "databricks",
        "s3-prefix",
        "databricks-prefix",
        "hf",
        "hf-prefix",
        "dropbox",
        "dropbox-root",
        "onedrive",
        "sharepoint",
        "sharepoint-prefix",
        "ssh",
        "nextcloud",
        "gdrive",
        "gdrive-folder"
      ],
      "command": "v=\"from var\"\ncat <<< \"$v\"",
      "expect": {
        "exit": 0,
        "stdout": "from var\n",
        "stderr": ""
      }
    },
    {
      "id": "herestring_wc",
      "seq": 501223,
      "targets": [
        "ram",
        "disk",
        "redis",
        "opfs",
        "s3",
        "databricks",
        "s3-prefix",
        "databricks-prefix",
        "hf",
        "hf-prefix",
        "dropbox",
        "dropbox-root",
        "onedrive",
        "sharepoint",
        "sharepoint-prefix",
        "ssh",
        "nextcloud",
        "gdrive",
        "gdrive-folder"
      ],
      "command": "wc -c <<< hi",
      "expect": {
        "exit": 0,
        "stdout": "3\n",
        "stderr": ""
      }
    },
    {
      "id": "herestring_tr",
      "seq": 501224,
      "targets": [
        "ram",
        "disk",
        "redis",
        "opfs",
        "s3",
        "databricks",
        "s3-prefix",
        "databricks-prefix",
        "hf",
        "hf-prefix",
        "dropbox",
        "dropbox-root",
        "onedrive",
        "sharepoint",
        "sharepoint-prefix",
        "ssh",
        "nextcloud",
        "gdrive",
        "gdrive-folder"
      ],
      "command": "tr a-z A-Z <<< abc",
      "expect": {
        "exit": 0,
        "stdout": "ABC\n",
        "stderr": ""
      }
    },
    {
      "id": "herestring_cmdsub",
      "seq": 501225,
      "targets": [
        "ram",
        "disk",
        "redis",
        "opfs",
        "s3",
        "databricks",
        "s3-prefix",
        "databricks-prefix",
        "hf",
        "hf-prefix",
        "dropbox",
        "dropbox-root",
        "onedrive",
        "sharepoint",
        "sharepoint-prefix",
        "ssh",
        "nextcloud",
        "gdrive",
        "gdrive-folder"
      ],
      "command": "cat <<< \"sub=$(echo x)\"",
      "expect": {
        "exit": 0,
        "stdout": "sub=x\n",
        "stderr": ""
      }
    },
    {
      "id": "herestring_read",
      "seq": 501226,
      "targets": [
        "ram",
        "disk",
        "redis",
        "opfs",
        "s3",
        "databricks",
        "s3-prefix",
        "databricks-prefix",
        "hf",
        "hf-prefix",
        "dropbox",
        "dropbox-root",
        "onedrive",
        "sharepoint",
        "sharepoint-prefix",
        "ssh",
        "nextcloud",
        "gdrive",
        "gdrive-folder"
      ],
      "command": "read -r a b <<< \"one two three\"\necho \"a=$a b=$b\"",
      "expect": {
        "exit": 0,
        "stdout": "a=one b=two three\n",
        "stderr": ""
      }
    },
    {
      "id": "herestring_empty",
      "seq": 501236,
      "targets": [
        "ram",
        "disk",
        "redis",
        "opfs",
        "s3",
        "databricks",
        "s3-prefix",
        "databricks-prefix",
        "hf",
        "hf-prefix",
        "dropbox",
        "dropbox-root",
        "onedrive",
        "sharepoint",
        "sharepoint-prefix",
        "ssh",
        "nextcloud",
        "gdrive",
        "gdrive-folder"
      ],
      "command": "wc -c <<< \"\"",
      "expect": {
        "exit": 0,
        "stdout": "1\n",
        "stderr": ""
      }
    },
    {
      "id": "herestring_unquoted_var",
      "seq": 501237,
      "targets": [
        "ram",
        "disk",
        "redis",
        "opfs",
        "s3",
        "databricks",
        "s3-prefix",
        "databricks-prefix",
        "hf",
        "hf-prefix",
        "dropbox",
        "dropbox-root",
        "onedrive",
        "sharepoint",
        "sharepoint-prefix",
        "ssh",
        "nextcloud",
        "gdrive",
        "gdrive-folder"
      ],
      "command": "hs='two words'; cat <<< $hs",
      "expect": {
        "exit": 0,
        "stdout": "two words\n",
        "stderr": ""
      }
    },
    {
      "id": "herestring_arith",
      "seq": 501238,
      "targets": [
        "ram",
        "disk",
        "redis",
        "opfs",
        "s3",
        "databricks",
        "s3-prefix",
        "databricks-prefix",
        "hf",
        "hf-prefix",
        "dropbox",
        "dropbox-root",
        "onedrive",
        "sharepoint",
        "sharepoint-prefix",
        "ssh",
        "nextcloud",
        "gdrive",
        "gdrive-folder"
      ],
      "command": "cat <<< $((4 * 5))",
      "expect": {
        "exit": 0,
        "stdout": "20\n",
        "stderr": ""
      }
    },
    {
      "id": "herestring_pipe_precedence",
      "seq": 501239,
      "targets": [
        "ram",
        "disk",
        "redis",
        "opfs",
        "s3",
        "databricks",
        "s3-prefix",
        "databricks-prefix",
        "hf",
        "hf-prefix",
        "dropbox",
        "dropbox-root",
        "onedrive",
        "sharepoint",
        "sharepoint-prefix",
        "ssh",
        "nextcloud",
        "gdrive",
        "gdrive-folder"
      ],
      "command": "printf 'pipe\\n' | cat <<< here",
      "expect": {
        "exit": 0,
        "stdout": "here\n",
        "stderr": ""
      }
    },
    {
      "id": "herestring_cmdsub_trim",
      "seq": 501240,
      "targets": [
        "ram",
        "disk",
        "redis",
        "opfs",
        "s3",
        "databricks",
        "s3-prefix",
        "databricks-prefix",
        "hf",
        "hf-prefix",
        "dropbox",
        "dropbox-root",
        "onedrive",
        "sharepoint",
        "sharepoint-prefix",
        "ssh",
        "nextcloud",
        "gdrive",
        "gdrive-folder"
      ],
      "command": "cat <<< \"$(printf 'x\\n\\n')\"",
      "expect": {
        "exit": 0,
        "stdout": "x\n",
        "stderr": ""
      }
    },
    {
      "id": "herestring_multiple_last",
      "seq": 501248,
      "targets": [
        "ram",
        "disk",
        "redis",
        "opfs",
        "s3",
        "databricks",
        "s3-prefix",
        "databricks-prefix",
        "hf",
        "hf-prefix",
        "dropbox",
        "dropbox-root",
        "onedrive",
        "sharepoint",
        "sharepoint-prefix",
        "ssh",
        "nextcloud",
        "gdrive",
        "gdrive-folder"
      ],
      "command": "cat <<< one <<< two",
      "expect": {
        "exit": 0,
        "stdout": "two\n",
        "stderr": ""
      }
    },
    {
      "id": "herestring_file_then_here",
      "seq": 501249,
      "targets": [
        "ram",
        "disk",
        "redis",
        "opfs",
        "s3",
        "databricks",
        "s3-prefix",
        "databricks-prefix",
        "hf",
        "hf-prefix",
        "dropbox",
        "dropbox-root",
        "onedrive",
        "sharepoint",
        "sharepoint-prefix",
        "ssh",
        "nextcloud",
        "gdrive",
        "gdrive-folder"
      ],
      "command": "printf 'file\\n' > /data/HSF1; cat < /data/HSF1 <<< here; rm /data/HSF1",
      "expect": {
        "exit": 0,
        "stdout": "here\n",
        "stderr": ""
      }
    },
    {
      "id": "herestring_here_then_file",
      "seq": 501250,
      "targets": [
        "ram",
        "disk",
        "redis",
        "opfs",
        "s3",
        "databricks",
        "s3-prefix",
        "databricks-prefix",
        "hf",
        "hf-prefix",
        "dropbox",
        "dropbox-root",
        "onedrive",
        "sharepoint",
        "sharepoint-prefix",
        "ssh",
        "nextcloud",
        "gdrive",
        "gdrive-folder"
      ],
      "command": "printf 'file\\n' > /data/HSF2; cat <<< here < /data/HSF2; rm /data/HSF2",
      "expect": {
        "exit": 0,
        "stdout": "file\n",
        "stderr": ""
      }
    },
    {
      "id": "herestring_no_split_glob",
      "seq": 501251,
      "targets": [
        "ram",
        "disk",
        "redis",
        "opfs",
        "s3",
        "databricks",
        "s3-prefix",
        "databricks-prefix",
        "hf",
        "hf-prefix",
        "dropbox",
        "dropbox-root",
        "onedrive",
        "sharepoint",
        "sharepoint-prefix",
        "ssh",
        "nextcloud",
        "gdrive",
        "gdrive-folder"
      ],
      "command": "hs='*  two'; cat <<< $hs",
      "expect": {
        "exit": 0,
        "stdout": "*  two\n",
        "stderr": ""
      }
    },
    {
      "id": "herestring_pipeline_left",
      "seq": 501252,
      "targets": [
        "ram",
        "disk",
        "redis",
        "opfs",
        "s3",
        "databricks",
        "s3-prefix",
        "databricks-prefix",
        "hf",
        "hf-prefix",
        "dropbox",
        "dropbox-root",
        "onedrive",
        "sharepoint",
        "sharepoint-prefix",
        "ssh",
        "nextcloud",
        "gdrive",
        "gdrive-folder"
      ],
      "command": "cat <<< abc | tr a-z A-Z",
      "expect": {
        "exit": 0,
        "stdout": "ABC\n",
        "stderr": ""
      }
    },
    {
      "id": "herestring_param_default",
      "seq": 501253,
      "targets": [
        "ram",
        "disk",
        "redis",
        "opfs",
        "s3",
        "databricks",
        "s3-prefix",
        "databricks-prefix",
        "hf",
        "hf-prefix",
        "dropbox",
        "dropbox-root",
        "onedrive",
        "sharepoint",
        "sharepoint-prefix",
        "ssh",
        "nextcloud",
        "gdrive",
        "gdrive-folder"
      ],
      "command": "hs=; cat <<< \"${hs:-fallback}\"",
      "expect": {
        "exit": 0,
        "stdout": "fallback\n",
        "stderr": ""
      }
    }
  ]
}
